{
    "OBJETOS":{

                "PLANOS":[

                            {
                                    "APG_COSTAS":false,    
                                    "MATERIAL":{
                                                "TIPO":"LAMBERTIANO",
                                                "TEXTURA" : "QUADRICULADA",
                                                "COR1":{
                                                        "R": 1,
                                                        "G": 0,
                                                        "B": 0     
                                                       },
                                                "COR2":{
                                                        "R": 0,
                                                        "G": 0,
                                                        "B": 1  
                                                }                                        
                                               },
                                    "V0":{
                                            "X": -1.5,
                                            "Y": 1,
                                            "Z": -1.5,
                                            "H": 1
                                         },
                                    "V1":{
                                            "X": -1.5,
                                            "Y": 1,
                                            "Z": 1.5,
                                            "H": 1
                                         },
                                    "V2":{
                                            "X": 1.5,
                                            "Y": 1,
                                            "Z": 1.5,
                                            "H": 1
                                         },
                                    "V3":{
                                            "X": 1.5,
                                            "Y": 1,
                                            "Z": -1.5,
                                            "H": 1
                                         }                                    
                                }

                         ]
              }
}